NanligongGaodengGongchengShuxueJiangyi/README.md
NanligongGaodengGongchengShuxueJiangyi/__init__.py
NanligongGaodengGongchengShuxueJiangyi/__main__.py
NanligongGaodengGongchengShuxueJiangyi/file.pdf
NanligongGaodengGongchengShuxueJiangyi/index.html
nanligong_gaodeng_gongcheng_shuxue_jiangyi-2024.3.4.0.dist-info/METADATA
nanligong_gaodeng_gongcheng_shuxue_jiangyi-2024.3.4.0.dist-info/WHEEL
nanligong_gaodeng_gongcheng_shuxue_jiangyi-2024.3.4.0.dist-info/entry_points.txt
nanligong_gaodeng_gongcheng_shuxue_jiangyi-2024.3.4.0.dist-info/top_level.txt
nanligong_gaodeng_gongcheng_shuxue_jiangyi-2024.3.4.0.dist-info/RECORD
